octo_pipeline_python/backends/yaml/__init__.py
octo_pipeline_python/backends/yaml/yaml_backend.py
octo_pipeline_python/backends/yaml/actions/__init__.py
octo_pipeline_python/backends/yaml/actions/yaml_lint_check.py
octo_pipeline_python/backends/yaml/models/__init__.py
octo_pipeline_python/backends/yaml/models/yaml_model.py
octo_pipeline_backend_yaml_python-1.3.2.dist-info/LICENSE.txt
octo_pipeline_backend_yaml_python-1.3.2.dist-info/METADATA
octo_pipeline_backend_yaml_python-1.3.2.dist-info/README.md
octo_pipeline_backend_yaml_python-1.3.2.dist-info/WHEEL
octo_pipeline_backend_yaml_python-1.3.2.dist-info/top_level.txt
octo_pipeline_backend_yaml_python-1.3.2.dist-info/RECORD
